<getHotels>
	<result>
		<address>Den Texstraat 16</address>
		<checkin>
			<from>15:00</from>
			<to />
		</checkin>
		<checkout>
			<from />
			<to>11:00</to>
		</checkout>
		<city>Amsterdam</city>
		<city_id>-2140479</city_id>
		<class>3</class>
		<class_is_estimated>0</class_is_estimated>
		<commission>0</commission>
		<contractchain_id />
		<countrycode>nl</countrycode>
		<created>0000-00-00 00:00:00</created>
		<currencycode>EUR</currencycode>
		<district />
		<exact_class>3.0</exact_class>
		<hotel_id>10003</hotel_id>
		<hoteltype_id>14</hoteltype_id>
		<is_closed>0</is_closed>
		<languagecode>en</languagecode>
		<location>
			<latitude>52.358834732828775</latitude>
			<longitude>4.893867373466492</longitude>
		</location>
		<max_persons_in_reservation>0</max_persons_in_reservation>
		<max_rooms_in_reservation>0</max_rooms_in_reservation>
		<maxrate>168</maxrate>
		<minrate>88</minrate>
		<name>Asterisk Hotel 3 stars</name>
		<nr_rooms>22</nr_rooms>
		<pagename>asterisk</pagename>
		<preferred>0</preferred>
		<ranking />
		<review_nr />
		<review_score />
		<url>http://www.booking.com/hotel/nl/asterisk.html</url>
		<zip>1017 ZA</zip>
	</result>
	<result>
		<address>Keizersgracht 164</address>
		<checkin>
			<from>14:00</from>
			<to />
		</checkin>
		<checkout>
			<from>07:00</from>
			<to>12:00</to>
		</checkout>
		<city>Amsterdam</city>
		<city_id>-2140479</city_id>
		<class>4</class>
		<class_is_estimated>0</class_is_estimated>
		<commission>0</commission>
		<contractchain_id />
		<countrycode>nl</countrycode>
		<created>0000-00-00 00:00:00</created>
		<currencycode>EUR</currencycode>
		<district />
		<exact_class>4.0</exact_class>
		<hotel_id>10004</hotel_id>
		<hoteltype_id>14</hoteltype_id>
		<is_closed>0</is_closed>
		<languagecode>en</languagecode>
		<location>
			<latitude>52.37585871041089</latitude>
			<longitude>4.886006489396095</longitude>
		</location>
		<max_persons_in_reservation>0</max_persons_in_reservation>
		<max_rooms_in_reservation>3</max_rooms_in_reservation>
		<maxrate>530</maxrate>
		<minrate>190</minrate>
		<name>The Toren</name>
		<nr_rooms>38</nr_rooms>
		<pagename>toren</pagename>
		<preferred>1</preferred>
		<ranking />
		<review_nr />
		<review_score />
		<url>http://www.booking.com/hotel/nl/toren.html</url>
		<zip>1015 CZ</zip>
	</result>
</getHotels>